[
  {
    "Title": "Soukaku's Hollow Rescue Report",
    "Author": "Emergency Response Team",
    "Price": 1.99,
    "Topic": "Rescue Operations in Hollows",
    "Duration": "00:12:34"
  },
  {
    "Title": "Wise's Hollow Field Notes",
    "Author": "Proxy Office",
    "Price": 3.50,
    "Topic": "Field Research & Proxy Strategy",
    "Duration": "00:18:20"
  },
  {
    "Title": "Belle's Personal Log: The Early Days",
    "Author": "Belle",
    "Price": 0.00,
    "Topic": "New Eridu History",
    "Duration": "00:09:47"
  }
]
